beamngpy/__init__.py
beamngpy/logging.py
beamngpy/types.py
beamngpy/version.txt
beamngpy/api/__init__.py
beamngpy/api/beamng/__init__.py
beamngpy/api/beamng/base.py
beamngpy/api/beamng/camera.py
beamngpy/api/beamng/control.py
beamngpy/api/beamng/debug.py
beamngpy/api/beamng/environment.py
beamngpy/api/beamng/platoon.py
beamngpy/api/beamng/scenario.py
beamngpy/api/beamng/settings.py
beamngpy/api/beamng/system.py
beamngpy/api/beamng/traffic.py
beamngpy/api/beamng/ui.py
beamngpy/api/beamng/vehicles.py
beamngpy/api/beamng/vehicles_ge.py
beamngpy/api/vehicle/__init__.py
beamngpy/api/vehicle/acc.py
beamngpy/api/vehicle/ai.py
beamngpy/api/vehicle/base.py
beamngpy/api/vehicle/couplers.py
beamngpy/api/vehicle/logging.py
beamngpy/api/vehicle/root.py
beamngpy/beamng/__init__.py
beamngpy/beamng/beamng.py
beamngpy/beamng/filesystem.py
beamngpy/connection/__init__.py
beamngpy/connection/comm_base.py
beamngpy/connection/connection.py
beamngpy/connection/prefixed_length_socket.py
beamngpy/misc/__init__.py
beamngpy/misc/colors.py
beamngpy/misc/quat.py
beamngpy/misc/vec3.py
beamngpy/scenario/__init__.py
beamngpy/scenario/level.py
beamngpy/scenario/procedural.py
beamngpy/scenario/road.py
beamngpy/scenario/scenario.py
beamngpy/scenario/scenario_object.py
beamngpy/sensors/GPS.py
beamngpy/sensors/__init__.py
beamngpy/sensors/advanced_IMU.py
beamngpy/sensors/configuration_helpers.py
beamngpy/sensors/damage.py
beamngpy/sensors/electrics.py
beamngpy/sensors/gforces.py
beamngpy/sensors/ideal_radar.py
beamngpy/sensors/lidar.py
beamngpy/sensors/map_sensor_configuration.py
beamngpy/sensors/mesh.py
beamngpy/sensors/powertrain_sensor.py
beamngpy/sensors/radar.py
beamngpy/sensors/roads_sensor.py
beamngpy/sensors/sensor.py
beamngpy/sensors/shmem.py
beamngpy/sensors/state.py
beamngpy/sensors/timer.py
beamngpy/sensors/ultrasonic.py
beamngpy/sensors/vehicle_feeder.py
beamngpy/sensors/vehicle_sensor_configuration.py
beamngpy/sensors/camera/__init__.py
beamngpy/sensors/camera/camera.py
beamngpy-1.34.1.dist-info/licenses/AUTHORS.rst
beamngpy-1.34.1.dist-info/licenses/LICENSE.txt
beamngpy-1.34.1.dist-info/METADATA
beamngpy-1.34.1.dist-info/WHEEL
beamngpy-1.34.1.dist-info/top_level.txt
beamngpy-1.34.1.dist-info/RECORD
