Metadata-Version: 2.4
Name: beamngpy
Version: 1.34.1
Summary: Python API to interact with BeamNG.tech.
Home-page: https://github.com/BeamNG/BeamNGpy
Author: BeamNG GmbH
Author-email: tech@beamng.gmbh
License: MIT
Platform: any
Classifier: Development Status :: 4 - Beta
Classifier: Programming Language :: Python
License-File: LICENSE.txt
License-File: AUTHORS.rst
Requires-Dist: numpy
Requires-Dist: msgpack
Requires-Dist: Pillow
Requires-Dist: Jinja2
Requires-Dist: scipy
Requires-Dist: matplotlib
Requires-Dist: seaborn
Dynamic: description
Dynamic: description-content-type
Dynamic: license-file
